sfdl_cluster/__init__.py
sfdl_cluster/cluster.py
sfdl_cluster-0.1.0.dist-info/METADATA
sfdl_cluster-0.1.0.dist-info/WHEEL
sfdl_cluster-0.1.0.dist-info/top_level.txt
sfdl_cluster-0.1.0.dist-info/RECORD
