Metadata-Version: 2.4
Name: sfdl-cluster
Version: 0.1.0
Summary: Same Features Different Label clustering tool with Calinski-Harabasz score
Author: Your Name
Author-email: you@example.com
Classifier: Programming Language :: Python :: 3
Requires-Dist: pandas
Requires-Dist: matplotlib
Requires-Dist: scikit-learn
Dynamic: author
Dynamic: author-email
Dynamic: classifier
Dynamic: requires-dist
Dynamic: summary
